{"q0": "2487ea51-9afd-42d5-81d1-7f4a6a086bbe", "q1": "кладовщик", "q2": "Не совсем", "q2d": 0, "q3": {"начальник склада": 89, "зам.начальника склада, начальник склада": 53}, "q4": ["fifo\\lifo"], "q5": ["ооо \"контракт сервис\" ( организация перевозок сборного груза по россии автомобильным и жд транспортом)", "зао \"бмт\" (беломортранс) организация перевозок сборного груза по россии автомобильным транспортом)", "зао \"беломортранс санкт-петербург\""], "q6": ["сортировка"], "q7": [], "q8": ["руководство"], "q9": ["руководство"], "q10": [43]}