{"q0": "349cdc64-41b3-4bd2-8bba-a637fcbe181c", "q1": "кладовщик", "q2": "Да", "q2d": 4, "q3": {"начальник склада": 11, "кладовщик склада з/частей автосервиса": 46, "кладовщик-операционист": 22}, "q4": ["internet"], "q5": ["ооо фортуна спб", "ооо\"невский лакокрасочный завод\"", "ооо \"интекс\"", "ооо \" такара\"", "ак \" грузомобиль\"", "ооо \" венера \"", "ооо \" балтийский хлеб \""], "q6": ["адресное"], "q7": ["word"], "q8": ["excel, internet"], "q9": ["дополнительные навыки: word, excel, internet"], "q10": [84]}