{"q0": "41a1e69e-79b0-418b-b576-54e062923d49", "q1": "кладовщик", "q2": "Не совсем", "q2d": 0, "q3": {"грузчик-комплектовщик": 96}, "q4": ["труд"], "q5": ["ооо стильная линия"], "q6": [], "q7": [], "q8": ["работа на складе.комплектация заказов.экспедиция.работа сдокументацией.уверенный пользователь пк. отмечен похвальной грамотой за добросовестный труд"], "q9": ["работа на складе.комплектация заказов.экспедиция.работа сдокументацией.уверенный пользователь пк. отмечен похвальной грамотой за добросовестный труд"], "q10": [70]}