{"q0": "444ec1a5-22c0-45d0-81f5-064bcb589d15", "q1": "кладовщик", "q2": "Не совсем", "q2d": 0, "q3": {"руководитель складской и транспортной логистики": 6, "начальник складов фабрики \"ригли\" (производство жевательной резинки) в с-петербурге": 227}, "q4": ["lean manufacturing"], "q5": ["magna cosma international, завод \"питерформ\"", "ооо \"ригли\""], "q6": ["адресной"], "q7": ["sap"], "q8": ["фабрика получила дипломы 1 и 2 ступени\n - внедрение lean manufacturing"], "q9": ["владение компьютером на уровне уверенного пользователя\n - действующая санитарная книжка\n - sap power user"], "q10": [36]}