{"q0": "4fefbb08-5d98-49cb-ba35-84a6fd37367f", "q1": "кладовщик", "q2": "Не совсем", "q2d": 0, "q3": {"помощник кладовщика": 7, "кладовщик-грузчик": 20}, "q4": ["товара"], "q5": ["зао технокрафт", "ооо август"], "q6": [], "q7": [], "q8": ["погрузочно-разгрузочные работы\n сбор товара по накладным\n инвентаризациипогрузочно- разгрузочные работы\n сбор товара по накладным\n упаковка товара"], "q9": ["погрузочно-разгрузочные работы\n сбор товара по накладным\n инвентаризациипогрузочно- разгрузочные работы\n сбор товара по накладным\n упаковка товара"], "q10": [84]}