{"q0": "55de1fb6-1a0f-4f8f-abd0-2c2414eda7fe", "q1": "кладовщик", "q2": "Не совсем", "q2d": 0, "q3": {"начальник склада": 9, "комплектовщик": 1, "кладовщик акцизного склада алкогольной продукции": 1}, "q4": ["операций"], "q5": ["ооо «дэфо - екатеринбург»", "ооо «глория джинс»", "ооо «автоваззапчасть»"], "q6": [], "q7": [], "q8": ["контроль разгрузок, отгрузок, контроль хранения товара"], "q9": ["контроль разгрузок, отгрузок, контроль хранения товара организация работы складских операций в подчинении 1 кладовщик"], "q10": [163]}