{"q0": "5ecabacc-571f-4321-acf5-d1fabcc5b024", "q1": "кладовщик", "q2": "Не совсем", "q2d": 0, "q3": {"инженер по складской работе": 4}, "q4": ["транспортных вагонов."], "q5": ["оао \"евраз находкинский морской торговый порт\""], "q6": [], "q7": [], "q8": ["организация и контроль работы на складских площадях.оперативное взаимодействие с маневровым диспетчером и ж/д группой"], "q9": ["организация и контроль работы на складских площадях.оперативное взаимодействие с маневровым диспетчером и ж/д группой"], "q10": [58]}