{"q0": "691e8677-149b-49ad-8529-262cf9400469", "q1": "кладовщик", "q2": "Да", "q2d": 17, "q3": {"администратор склада": 37, "старший кладовщик": 5}, "q4": ["ведение отчётности.контроль"], "q5": ["алиди, группа компаний", "юлмарт", "юлмарт", "юлмарт", "элсо группа, группа компаний", "ооо *графт-трейдинг*"], "q6": [], "q7": ["sap"], "q8": ["хранения,учёт товарапланирование,контроль выполнение задач персоналом в подчинении"], "q9": ["организация хранения,учёт товарапланирование,контроль выполнение задач персоналом в подчинении"], "q10": [43]}