{"q0": "803153ea-27ed-477f-b38e-f8a42116b6e8", "q1": "кладовщик", "q2": "Не совсем", "q2d": 0, "q3": {"оператор склада": 87}, "q4": ["отгрузку, учет накладных, ведение сертификационной базы, внесение коррекций в накладные."], "q5": ["ооо\"маркет аг\""], "q6": [], "q7": [], "q8": ["накладных на отгрузку, учет накладных, ведение сертификационной базы, внесение коррекций в накладные"], "q9": ["распечатка накладных на отгрузку, учет накладных, ведение сертификационной базы, внесение коррекций в накладные"], "q10": [0]}