{"q0": "8cc123a6-4258-4a2b-ae62-05278043a72c", "q1": "кладовщик", "q2": "Не совсем", "q2d": 0, "q3": {"бухгалтер-операционист склада самовывоза": 48}, "q4": ["microsoft"], "q5": ["ооо \"компания хк мвд и марвел\""], "q6": [], "q7": ["axapta", "microsoft dynamics ax"], "q8": ["формирование первичных учетных документов и отгрузка товара с использованием программы microsoft dynamics ax (axapta)"], "q9": ["формирование первичных учетных документов и отгрузка товара с использованием программы microsoft dynamics"], "q10": [0]}