{"q0": "9048454f-cbd4-4833-93cc-828a32fff25a", "q1": "кладовщик", "q2": "Не совсем", "q2d": 0, "q3": {"работник склада": 8}, "q4": ["прием невостребованных заказов,проверка документации,помощь в отправке заказов по торговым точкам."], "q5": ["е5.ру"], "q6": [], "q7": [], "q8": ["прием невостребованных заказов,проверка документации,помощь в отправке заказов по торговым точкам"], "q9": ["прием невостребованных заказов,проверка документации,помощь в отправке заказов по торговым точкам"], "q10": [76]}