{"q0": "93b43110-0e11-48c1-9a36-77e772810ee2", "q1": "кладовщик", "q2": "Не совсем", "q2d": 0, "q3": {"начальник склада обособленное подразделение питерское": 62, "начальник склада": 62, "зам.нач.склада  затем начальник склада": 18}, "q4": ["складе"], "q5": ["ооо савушкин продукт-москва", "ооо рельеф спб", "ооо бамбино детские игрушки", "ооо \"арт-скальт\""], "q6": ["адресное"], "q7": [], "q8": ["руководство коллективом склада до 10 человек"], "q9": ["руководство коллективом склада до 10 человек"], "q10": [31]}