{"q0": "95039fe8-b53d-4e4f-84de-8fa627093c54", "q1": "кладовщик", "q2": "Не совсем", "q2d": 0, "q3": {"продавец-кладовщик": 9}, "q4": ["покупателей, сортировка товара на складе, приемка товара, участие в инвентаризациях"], "q5": ["магазин \"субстанция\""], "q6": ["сортировка"], "q7": [], "q8": ["покупателей, сортировка товара на складе, приемка товара, участие в инвентаризациях"], "q9": ["консультирование покупателей, сортировка товара на складе, приемка товара, участие в инвентаризациях"], "q10": [142]}