{"q0": "b723681d-acb3-401b-895d-cdeaa34e3179", "q1": "кладовщик", "q2": "Не совсем", "q2d": 0, "q3": {"грузчик-комплектовщик": 13}, "q4": ["сбор товара по накладным, перемещение товара на складе, помощь в погрузке-разгрузке машин"], "q5": ["ооо фм ложистик серебрянка"], "q6": [], "q7": [], "q8": ["сбор товара по накладным, перемещение товара на складе, помощь в погрузке-разгрузке машин"], "q9": ["сбор товара по накладным, перемещение товара на складе, помощь в погрузке-разгрузке машин"], "q10": [74]}