{"q0": "ca5b02ec-b110-4649-9308-b3e98fa9ca38", "q1": "кладовщик", "q2": "Не совсем", "q2d": 0, "q3": {"руководитель отдела складской логистики (менеджер проекта склада)": 3, "начальник отдела складской логистики": 21, "управляющий складским комплексом": 40}, "q4": ["выбор"], "q5": ["ооо «торговый дом северо-западный» («магазины 220вольт») -дистрибуция электроинструмента", "ооо «мясные деликатесы» (гк «рубеж») , бренд “шеф повар» - мясоперерабатывающее производство", "зао «генезис» - фармацевтический холдинг – продажа лекарственных препаратов"], "q6": ["стеллажного", "ассортимента"], "q7": ["курс", "бухта"], "q8": ["бухта и csb inventory"], "q9": ["должностные"], "q10": [129]}