{"q0": "e429f904-e80f-43e8-b265-fd08654c2c5f", "q1": "кладовщик", "q2": "Не совсем", "q2d": 0, "q3": {"комплектовщик": 55}, "q4": ["хоз.средств.,был удостоен звания лучший сотрудник года.работал в качестве старшего смены."], "q5": ["ооо теремок-русские блины"], "q6": [], "q7": [], "q8": ["продуктов питания и хоз.средств.,был удостоен звания лучший сотрудник года.работал в качестве старшего смены"], "q9": ["комплектация продуктов питания и хоз.средств.,был удостоен звания лучший сотрудник года.работал в качестве старшего смены"], "q10": [54]}