{"q0": "e8038711-615a-4dce-b8bc-1ff3e83038f6", "q1": "кладовщик", "q2": "Не совсем", "q2d": 0, "q3": {"ведущий специалист складских технологий": 3, "оператор складского учета": 15}, "q4": ["outlook"], "q5": ["алиди, группа компаний", "алиди, группа компаний", "ресторан \"санкт-петербург\" наб. канала грибоедова 7", "гранд отель европа", "кортъярд санкт-петербург васильевский", "отель санкт-петербург (пироговская наб.5)"], "q6": [], "q7": ["word", "outlook", "ms office"], "q8": ["работа в специализированной программе складского учета wms\n складской учет, ведению базы данных по товару"], "q9": ["уверенный пользователь пк, ms office"], "q10": [38]}