{"q0": "e9d32623-e981-4bd2-a5ef-a53617730469", "q1": "кладовщик", "q2": "Да", "q2d": 2, "q3": {"менеджер складского учёта": 8, "менеджер складского учета": 13, "дозировщик 3 р. приёмосдатчик кладовщик": 39}, "q4": ["получение‚"], "q5": ["нпф завод измерон", "ооо цнти прогресс", "ооо фрикадельки сеть ресторанов", "ооо \" фирма вероника лтд\"", "ооо \"комус\"", "оао \"каравай\""], "q6": [], "q7": ["tillypad"], "q8": ["получение‚ хранение и отпуск материальных ценностей"], "q9": ["получение‚"], "q10": [68]}