{"q0": "fe5b3c81-5949-4bfc-a14a-7d6be696637e", "q1": "кладовщик", "q2": "Не совсем", "q2d": 0, "q3": {"директор по закупкам  (закупки, транспортная и складская логистика)": 21, "коммерческий директор (закупки, транспортная и складская логистика, складское хозяйство, вэд)": 31, "коммерческий директор  (закупки, транспортная и складская логистика, складское хозяйство)": 58}, "q4": ["формирование стратегии закупок и ведения закупочной деятельности; \n • проведение"], "q5": ["ооо \"фортис\"", "тоо \"самрук энерго инжиниринг\"", "экибастузская \"грэс-1\"", "тоо \"богатырь транс\""], "q6": [], "q7": ["курс"], "q8": ["формирование стратегии закупок и ведения закупочной деятельности"], "q9": ["формирование"], "q10": [0]}